{
	"__rethinkdb__": {
		"auto_primary": false,
		"db": "axegains",
		"host": "primary",
		"indexes": {},
		"primary": "_thrower",
		"table": "watl_match_stats"
	},
	"__name__": "WATL_Match_Stats",
	"_thrower": {"__type__":"uuid"},
	"matches": "uint",
	"points": "uint",
	"wins": "uint",
	"losses": "uint",
	"sixtyfours": "uint",
	"ksLeft": {
		"attempts": "uint",
		"drops": "uint",
		"hits": "uint"
	},
	"ksRight": {
		"attempts": "uint",
		"drops": "uint",
		"hits": "uint"
	},
	"regular": {
		"attempts": "uint",
		"drops": "uint",
		"sixes": "uint",
		"fours": "uint",
		"threes": "uint",
		"twos": "uint",
		"ones": "uint",
		"zeros": "uint"
	}
}
